stoltzmaniac/.DS_Store
stoltzmaniac/__init__.py
stoltzmaniac/data_handler/__init__.py
stoltzmaniac/data_handler/base.py
stoltzmaniac/data_handler/scale_data.py
stoltzmaniac/data_handler/test_train_split_data.py
stoltzmaniac/models/__init__.py
stoltzmaniac/models/supervised/__init__.py
stoltzmaniac/models/supervised/k_nearest_neighbors.py
stoltzmaniac/models/supervised/linear_regression.py
stoltzmaniac/utils/__init__.py
stoltzmaniac/utils/distance_functions.py
stoltzmaniac-0.2.0.dist-info/WHEEL
stoltzmaniac-0.2.0.dist-info/METADATA
stoltzmaniac-0.2.0.dist-info/RECORD
