Metadata-Version: 2.1
Name: stoltzmaniac
Version: 0.2.0
Summary: A lightweight library for basic machine learning tasks.
Home-page: https://github.com/stoltzmaniac/stoltzmaniac
Keywords: stoltzmaniac
Author: stoltzmaniac
Author-email: scott@stoltzmaniac.com
Requires-Python: >=3.7,<4.0
Classifier: Programming Language :: Python :: 3
Classifier: Programming Language :: Python :: 3.7
Classifier: Programming Language :: Python :: 3.8
Requires-Dist: numpy (>=1.18.4,<2.0.0)
Requires-Dist: pandas (>=1.0.4,<2.0.0)
Project-URL: Repository, https://github.com/stoltzmaniac/stoltzmaniac
